issue_solver/__init__.py
issue_solver/clock.py
issue_solver/factories.py
issue_solver/logging_config.py
issue_solver/agents/__init__.py
issue_solver/agents/agent_message_store.py
issue_solver/agents/anthropic_agent.py
issue_solver/agents/claude_code_agent.py
issue_solver/agents/claude_code_docs_agent.py
issue_solver/agents/coding_agent.py
issue_solver/agents/docs_prompts.py
issue_solver/agents/issue_resolving_agent.py
issue_solver/agents/openai_agent.py
issue_solver/agents/resolution_approaches.py
issue_solver/agents/supported_agents.py
issue_solver/agents/swe_agents_on_docker.py
issue_solver/agents/tools/__init__.py
issue_solver/agents/tools/anthropic_tools_schema.py
issue_solver/agents/tools/base.py
issue_solver/agents/tools/bash.py
issue_solver/agents/tools/collection.py
issue_solver/agents/tools/edit.py
issue_solver/agents/tools/openai_tools_schema.py
issue_solver/agents/tools/run.py
issue_solver/cli/__init__.py
issue_solver/cli/__main__.py
issue_solver/cli/cudu_cli.py
issue_solver/cli/dependencies.py
issue_solver/cli/index_repository_command.py
issue_solver/cli/prepare_command.py
issue_solver/cli/review_command.py
issue_solver/cli/solve_command.py
issue_solver/cli/solve_command_settings.py
issue_solver/cli/webhook_notifying_agent_message_store.py
issue_solver/cli/webhook_notifying_event_store.py
issue_solver/database/__init__.py
issue_solver/database/init_event_store.py
issue_solver/database/postgres_agent_message_store.py
issue_solver/database/postgres_event_store.py
issue_solver/database/migrations/README
issue_solver/database/migrations/__init__.py
issue_solver/database/migrations/env.py
issue_solver/database/migrations/script.py.mako
issue_solver/database/migrations/versions/2025_03_21_2354-598646fdaeb0_create_event_store_table.py
issue_solver/database/migrations/versions/2025_06_22_1841-45946eed8e9f_encrypt_existing_access_tokens.py
issue_solver/database/migrations/versions/2025_07_18_1202-02e08c46ffff_create_agent_message_store_table.py
issue_solver-0.1.14.dist-info/METADATA
issue_solver-0.1.14.dist-info/WHEEL
issue_solver-0.1.14.dist-info/entry_points.txt
issue_solver-0.1.14.dist-info/RECORD
